NetSuite_Connector/NetSuite.py
NetSuite_Connector/ODBC.py
NetSuite_Connector/__init__.py
NetSuite_Connector-0.2.2.dist-info/LICENSE
NetSuite_Connector-0.2.2.dist-info/METADATA
NetSuite_Connector-0.2.2.dist-info/WHEEL
NetSuite_Connector-0.2.2.dist-info/top_level.txt
NetSuite_Connector-0.2.2.dist-info/RECORD
