Metadata-Version: 2.1
Name: NetSuite-Connector
Version: 0.2.2
Summary: NetSuite Connector
Author-email: Marcos Lopez <merick16@gmail.com>
License: MIT License
Project-URL: Homepage, https://github.com/IngMarcosLopez/NetSuite-Connector
Project-URL: Bug Tracker, https://github.com/IngMarcosLopez/NetSuite-Connector/issues
Classifier: Programming Language :: Python :: 3
Classifier: License :: OSI Approved :: MIT License
Classifier: Operating System :: OS Independent
Requires-Python: >=3.7
License-File: LICENSE
